{
    "<pad>": 0,
    "<unk>": 1,
    "<s>": 2,
    "</s>": 3,
    "0": 4,
    ".": 5,
    "1": 6,
    "2": 7,
    "3": 8,
    "6": 9,
    "5": 10,
    "4": 11,
    "7": 12,
    "8": 13,
    "error>": 14,
    "<worst": 15,
    "<mean": 16,
    "9": 17,
    "texture>": 18,
    "symmetry>": 19,
    "smoothness>": 20,
    "radius>": 21,
    "points>": 22,
    "perimeter>": 23,
    "fractal": 24,
    "dimension>": 25,
    "concavity>": 26,
    "concave": 27,
    "compactness>": 28,
    "area>": 29,
    "points": 30,
    "dimension": 31,
    "<texture": 32,
    "<symmetry": 33,
    "<smoothness": 34,
    "<radius": 35,
    "<perimeter": 36,
    "<fractal": 37,
    "<concavity": 38,
    "<concave": 39,
    "<compactness": 40,
    "<area": 41
}